sphinx_ifelse/__init__.py
sphinx_ifelse/directives.py
sphinx_ifelse/ifelse.py
sphinx_ifelse/utils.py
sphinx_ifelse-0.11.2.dist-info/licenses/LICENSE
sphinx_ifelse-0.11.2.dist-info/WHEEL
sphinx_ifelse-0.11.2.dist-info/METADATA
sphinx_ifelse-0.11.2.dist-info/RECORD
