Metadata-Version: 2.4
Name: sphinx-ifelse
Version: 0.11.2
Summary: Sphinx extension for alternating content based on configuration values.
Author-email: Team X-As-Code <info@x-as-code.org>
Requires-Python: >=3.9,<4
License-Expression: EUPL-1.2
Classifier: Development Status :: 3 - Alpha
Classifier: Intended Audience :: Developers
Classifier: Framework :: Sphinx :: Extension
Classifier: Operating System :: OS Independent
Classifier: Programming Language :: Python
Classifier: Programming Language :: Python :: 3
Classifier: Programming Language :: Python :: 3.9
Classifier: Programming Language :: Python :: 3.10
Classifier: Programming Language :: Python :: 3.11
Classifier: Programming Language :: Python :: 3.12
Classifier: Programming Language :: Python :: 3.13
Classifier: Programming Language :: Python :: 3.14
Classifier: Topic :: Documentation
Classifier: Topic :: Utilities
License-File: LICENSE
Requires-Dist: sphinx>=7.4,<9
Project-URL: Documentation, https://x-as-code.github.io/sphinx-ifelse
Project-URL: Repository, https://github.com/x-as-code/sphinx-ifelse
